iNotes/AI.py
iNotes/__init__.py
iNotes/main.py
iNotes/summarize.py
inotes-1.5.2.dist-info/METADATA
inotes-1.5.2.dist-info/WHEEL
inotes-1.5.2.dist-info/entry_points.txt
inotes-1.5.2.dist-info/top_level.txt
inotes-1.5.2.dist-info/RECORD
