Metadata-Version: 2.4
Name: iNotes
Version: 1.5.2
Summary: iNotes is a simple Python package that uses AI to generate  clear, concise notes from just topics or summarize long documents. It's designed to assist students, professionals, and researchers in make short notes easily.
Author: TejusDubey
License: MIT
Classifier: Programming Language :: Python
Classifier: Operating System :: OS Independent
Requires-Dist: reportlab
Requires-Dist: requests
Requires-Dist: python-docx
Requires-Dist: pdfplumber
Dynamic: author
Dynamic: classifier
Dynamic: description
Dynamic: description-content-type
Dynamic: license
Dynamic: requires-dist
Dynamic: summary
